{
  "connection": "default",
  "collectionName": "",
  "info": {
    "name": "post",
    "description": ""
  },
  "options": {
    "timestamps": true
  },
  "attributes": {
    "title": {
      "default": "",
      "type": "string"
    },
    "week": {
      "default": "",
      "type": "integer"
    },
    "publish_date": {
      "default": "",
      "type": "date"
    },
    "body": {
      "default": "",
      "type": "text"
    },
    "image": {
      "model": "file",
      "via": "related",
      "plugin": "upload",
      "required": false
    }
  }
}